LICENSE
README.md
aioutilities/__init__.py
aioutilities/pool/__init__.py
aioutilities/pool/example.py
aioutilities/pool/pool.py
aioutilities/pool/task.py
aioutilities/pool/terminate.py
aioutilities-1.0.3.dist-info/entry_points.txt
aioutilities-1.0.3.dist-info/LICENSE
aioutilities-1.0.3.dist-info/WHEEL
aioutilities-1.0.3.dist-info/METADATA
aioutilities-1.0.3.dist-info/RECORD
