Metadata-Version: 2.1
Name: aioutilities
Version: 1.0.3
Summary: asyncio-powered coroutine worker pool
Home-page: https://github.com/kkirsche/aioutilities
License: MIT
Author: Kevin Kirsche
Author-email: kev.kirsche@gmail.com
Requires-Python: >=3.8,<4
Classifier: License :: OSI Approved :: MIT License
Classifier: Programming Language :: Python :: 3
Classifier: Programming Language :: Python :: 3.10
Classifier: Programming Language :: Python :: 3.8
Classifier: Programming Language :: Python :: 3.9
Project-URL: Repository, https://github.com/kkirsche/aioutilities
